AUTHORS.rst
CONTRIBUTING.rst
HISTORY.rst
LICENSE
MANIFEST.in
README.md
setup.py
PARpy/__init__.py
PARpy/parse.py
PARpy/sun_filter.py
PARpy.egg-info/PKG-INFO
PARpy.egg-info/SOURCES.txt
PARpy.egg-info/dependency_links.txt
PARpy.egg-info/not-zip-safe
PARpy.egg-info/requires.txt
PARpy.egg-info/top_level.txt