Metadata-Version: 1.1
Name: PARpy
Version: 0.1.0
Summary: Processing tool for PAR data of Satlantic Radiometers
Home-page: https://github.com/Grupo-de-Oceanografia-Costeira/PARpy
Author: Arnaldo Russo
Author-email: arnaldorusso@gmail.com
License: PSF
Keywords: PAR Photosynthetically Active Radiance Light Solar Angle
Platform: UNKNOWN
Classifier: Development Status :: 2 - Pre-Alpha
Classifier: Intended Audience :: Science/Research
Classifier: License :: OSI Approved :: Python Software Foundation License
Classifier: Programming Language :: Python :: 2.7
Classifier: Topic :: Scientific/Engineering :: Atmospheric Science
